pandes2/Backtracking.txt
pandes2/DP.txt
pandes2/Greedy.txt
pandes2/__init__.py
pandes2/all.txt
pandes2/divideAndConquer.txt
pandes2/recursiveNonrecursive.txt
pandes2/stringMatching.txt
pandes2-0.2.1.dist-info/licenses/LICENSE
pandes2-0.2.1.dist-info/METADATA
pandes2-0.2.1.dist-info/WHEEL
pandes2-0.2.1.dist-info/top_level.txt
pandes2-0.2.1.dist-info/RECORD
