Metadata-Version: 2.4
Name: pandes2
Version: 0.2.1
Summary: A sample package that prints text file content
Author: Micheal Scofield
Classifier: Programming Language :: Python :: 3
License-File: LICENSE
Dynamic: author
Dynamic: classifier
Dynamic: description
Dynamic: description-content-type
Dynamic: license-file
Dynamic: summary
